LICENSE.txt
MANIFEST.in
setup.py
_eSSP/Makefile
_eSSP/init.c
_eSSP/linux.c
_eSSP/port_linux.h
_eSSP/ssp_helpers.c
_eSSP/ssp_helpers.h
_eSSP/inc/SSPComs.h
_eSSP/inc/itl_types.h
_eSSP/inc/ssp_defines.h
_eSSP/lib/Encryption.c
_eSSP/lib/Encryption.h
_eSSP/lib/ITLSSPProc.c
_eSSP/lib/ITLSSPProc.h
_eSSP/lib/Makefile
_eSSP/lib/Random.c
_eSSP/lib/Random.h
_eSSP/lib/SSPComs.c
_eSSP/lib/SSPComs.c.bak
_eSSP/lib/SSPDownload.c
_eSSP/lib/defs.h
_eSSP/lib/enctest.c
_eSSP/lib/serialfunc.c
_eSSP/lib/serialfunc.h
_eSSP/lib/ssp_commands.c
eSSP/__init__.py
eSSP/constants.py
eSSP/eSSP.py
eSSP6.egg-info/PKG-INFO
eSSP6.egg-info/SOURCES.txt
eSSP6.egg-info/dependency_links.txt
eSSP6.egg-info/requires.txt
eSSP6.egg-info/top_level.txt