Metadata-Version: 1.0
Name: eSSP6
Version: 1.0.8
Summary: Encrypted Smiley Secure Protocol Python 3 Implementation
Home-page: https://github.com/Minege/eSSP
Author: Loan & Innovative Technology (Some of the C code)
Author-email: minege@protonmail.com
License: MIT
Platform: cygwin
Platform: osx
